[
  {
    "id": "2",
    "ten": "Latte Art Chuẩn Barista",
    "tieuDe": "Với người yêu cà phê espresso, latte art không chỉ là thức uống thơm ngon mà còn là một tác phẩm nghệ thuật thu nhỏ thú vị. ...",
    "hinh": "https://image.cooky.vn/recipe/g6/55850/s640/b4677e1f-60be-4091-a9c4-b4bfcf2ecc73.jpeg",
    "tieuDeChiTiet": "Với người yêu cà phê espresso, latte art không chỉ là thức uống thơm ngon mà còn là một tác phẩm nghệ thuật thu nhỏ thú vị. Mỗi ly latte gửi gắm tất cả kinh nghiệm, kỹ năng và tình yêu của người barista dành cho cà phê. Mời bạn cùng Cooky khám phá cách một barista chuyên nghiệp chuẩn bị một ly latte art nhé! ",
    "nguyenLieu": "Cà phê hạt\n\nSữa thanh trùng Đà Lạt Milk",
    "soLuong": "18gr\n\n200ml",
    "buoc1": "Bước 1: Xay hạt cà phê đang rang bằng máy xay chuyên dụng. Lấy một lượng cà phê bột khoảng 18gr. Dùng tamper để nén café sau đó gắn vào máy và bắt đầu chiết xuất nước cốt cà phê. Phần cà phê đậm đặc này sẽ có một lớp mỏng sánh màu nâu trên bề mặt, được gọi là crema. Khi bọt sữa màu trắng nổi lên và tiếp xúc với lớp crema sẽ tạo nên sự tương phản về màu sắc. Lưu ý, không để bột cà phê tiếp xúc lâu với không khí sẽ khiến cà phê giảm hương vị.",
    "hinh1b1": "https://image.cooky.vn/recipe/g6/55850/s240x240/b5ffcb09-0baa-484d-8a6c-b43a04618a3e.jpeg",
    "hinh2b1": "https://image.cooky.vn/recipe/g6/55850/s240x240/5cba6cf5-4a2c-45ca-965f-4effaad6a3bf.jpeg",
    "hinh3b1": "https://image.cooky.vn/recipe/g6/55850/s240x240/418cdaea-ef83-456b-af74-013c3432afca.jpeg",
    "buoc2": "Bước 2: Tạo bọt sữa: Xả vòi hơi trước khi tạo bọt sữa rồi dùng khăn lau sạch hơi nước và cố định vòi. Cho khoảng 200ml sữa tươi thanh trùng Dalat Milk lạnh vào ca. Đặt ca sữa vào vòi tạo bọt, để vòi lật qua một bên rồi bật vòi tạo bọt trong thời gian từ 10 - 15 giây. Quan sát thấy bọt sữa sánh mịn, nhiệt độ sữa vào khoảng 65 độ C là đạt chuẩn. Bạn có thể sử dụng nhiệt kế để đo chính xác nhiệt độ. Khi đã tạo bọt thành công, bạn chọn chế độ xả nước để vệ sinh vòi sạch sẽ. Sau đó, gõ nhẹ ca sữa để làm vỡ các bọt khí lớn rồi lắc nhẹ để bọt sữa quyện đều vào nhau.",
    "hinh1b2": "https://image.cooky.vn/recipe/g6/55850/s240x240/672f3aff-077c-497a-b026-26a3913560ce.jpeg",
    "hinh2b2": "https://image.cooky.vn/recipe/g6/55850/s240x240/b5d73c66-e013-441b-8904-db35788704dd.jpeg",
    "hinh3b2": null,
    "buoc3": "Bước 3: Nghiêng cốc cà phê 45 độ, nâng cao ca sữa đã tạo bọt và rót từ từ vào ly cà phê để trộn đều 2 nguyên liệu cho đến khi hỗn hợp chạm vào thành cốc thì dừng. Tiếp đến, đặt ca vào thành cốc, rót nhẹ nhàng để bọt sữa nổi lên mặt vào tạo hình tùy thích, vừa rót vừa ngửa cốc trở lại để hỗn hợp không bị tràn ra ngoài.",
    "hinh1b3": "https://image.cooky.vn/recipe/g6/55850/s240x240/e56671a9-342e-4283-a048-e2e02a11946a.jpeg",
    "hinh2b3": "https://image.cooky.vn/recipe/g6/55850/s240x240/6b67d369-92c4-4786-a2c5-c54678a6f987.jpeg",
    "hinh3b3": null,
    "buoc4": "Bước 4: Chỉ cần một chút khéo léo, ly latte art như thêm sức sống với những họa tiết bắt mắt khiến người thưởng thức không chỉ say mê hương vị cà phê mà còn bị cuốn hút bởi vẻ đẹp từ những hình vẽ đầy tinh tế.",
    "hinh1b4": "https://image.cooky.vn/recipe/g6/55850/s240x240/f19f8ded-3ada-44c9-8c80-53d655dd4a4a.jpeg",
    "hinh2b4": "https://image.cooky.vn/recipe/g6/55850/s240x240/cd01ee31-8e82-4484-ab7c-3ce8649a2dbe.jpeg",
    "hinh3b4": "https://image.cooky.vn/recipe/g6/55850/s240x240/3d459547-7503-40c8-82fb-5302f8531893.jpeg",
    "buoc5": null,
    "hinh1b5": null,
    "hinh2b5": null,
    "hinh3b5": null
  },
  {
    "id": "4",
    "ten": "Cà Phê Cold Brew Macchiato",
    "tieuDe": "Cà phê ủ lạnh - Cold brew đã dần trở nên phổ biến và được nhiều người yêu thích bởi cách chiết xuất độc đáo cùng hương vị thơm ngon. ...",
    "hinh": "https://image.cooky.vn/recipe/g6/55855/s240x240/32456aec-8871-46cc-8eaa-8c6f962386f1.jpeg",
    "tieuDeChiTiet": "Cà phê ủ lạnh - Cold brew đã dần trở nên phổ biến và được nhiều người yêu thích bởi cách chiết xuất độc đáo cùng hương vị thơm ngon. Thức uống này hoàn toàn có thể làm tại nhà với những dụng cụ đơn giản. Cooky sẽ hướng dẫn bạn cách ủ cold brew nhanh gọn và chế biến cold brew macchiato với vị béo đắng mới lạ vô cùng hấp dẫn.",
    "nguyenLieu": "Cà phê xay thô\n\nNước lọc\n\nSữa tươi thanh trùng Dalat Milk\n\nKem béo\n\nĐá viên",
    "soLuong": "60gr\n\n600ml\n\n30ml\n\n50ml\n\n",
    "buoc1": "Bước 1: Ủ cà phê: Cho vào bình pha cold brew 60gr cà phê xay thô, 600ml nước đun sôi để nguội, đậy nắp và ủ trong ngăn mát tủ lạnh 24 tiếng để cà phê lên men và có vị chua nhẹ như nước trái cây. Nếu không có bình pha chuyên dụng, bạn có thể ủ trong một chiếc bình thủy tinh, sau đó lọc cà phê qua túi lọc. Cách này vẫn thu được những ly cold brew thơm ngon.",
    "hinh1b1": "https://image.cooky.vn/recipe/g6/55855/s240x240/26c178ff-005b-40c3-b083-0fbebac503ce.jpeg",
    "hinh2b1": "https://image.cooky.vn/recipe/g6/55855/s240x240/897936f4-734d-4088-b53b-5943e04cd368.jpeg",
    "hinh3b1": "https://image.cooky.vn/recipe/g6/55855/s240x240/e1a59d22-9c33-4bcf-b417-fe2cd57401bb.jpeg",
    "buoc2": "Bước 2: Làm macchiato: Cho vào bình lắc 30ml sữa tươi thanh trùng Đà Lạt Milk, 50ml kem béo, 2 viên đá viên rồi đậy nắp, lắc thật mạnh tay đến khi hỗn hợp hòa quyện.",
    "hinh1b2": "https://image.cooky.vn/recipe/g6/55855/s240x240/44a6b3c7-0981-4da0-af0e-44344877350f.jpeg",
    "hinh2b2": "https://image.cooky.vn/recipe/g6/55855/s240x240/b553dff6-61b2-4a13-99cf-48abf005aca2.jpeg",
    "hinh3b2": "https://image.cooky.vn/recipe/g6/55855/s240x240/0086ea1e-b906-4902-8da4-7ac064ab1dfc.jpeg",
    "buoc3": "Bước 3: Thành phẩm: Cho đá viên vào ly, rót vào 300ml cà phê cold brew, thêm machhiato lên mặt là có thể thưởng thức.",
    "hinh1b3": "https://image.cooky.vn/recipe/g6/55855/s240x240/67299229-b470-49be-99a2-9ad821f4135b.jpeg",
    "hinh2b3": "https://image.cooky.vn/recipe/g6/55855/s240x240/3760720e-0e22-4768-9f4f-31dd511b20a9.jpeg",
    "hinh3b3": null,
    "buoc4": "Bước 4: Cold brew macchiato thơm nhẹ hương cà phê, có vị đắng dễ chịu kết hợp với macchito béo mịn tạo nên một thức uống ngon miệng và sành điệu.",
    "hinh1b4": "https://image.cooky.vn/recipe/g6/55855/s240x240/32456aec-8871-46cc-8eaa-8c6f962386f1.jpeg",
    "hinh2b4": "https://image.cooky.vn/recipe/g6/55855/s240x240/2b84b4d0-56fc-4004-8729-81e1b53d54a8.jpeg",
    "hinh3b4": "https://image.cooky.vn/recipe/g6/55855/s240x240/2a8a3567-628a-440b-a676-8c4fddc7529b.jpeg",
    "buoc5": null,
    "hinh1b5": null,
    "hinh2b5": null,
    "hinh3b5": null
  },
  {
    "id": "6",
    "ten": "Homemade Cappuccino",
    "tieuDe": "Hương cà phê chuẩn vị với lớp bọt sữa bồng bềnh giúp cho cappuccino được nhiều người yêu thích. ...",
    "hinh": "https://image.cooky.vn/recipe/g6/55849/s640/cb69c8f5-4561-4f0f-9dca-0f727007a852.jpeg",
    "tieuDeChiTiet": "Hương cà phê chuẩn vị với lớp bọt sữa bồng bềnh giúp cho cappuccino được nhiều người yêu thích. Với cách pha nhanh gọn bằng bình French Fress, bạn vẫn có thể chiết suất được cà phê tươi ngon, đồng thời tạo được lớp bọt sữa mịn rất đơn giản ngay tại nhà. Cùng Cooky thực hiện nhé!",
    "nguyenLieu": "Cà phê xay thô\n\nNước sôi\n\nSữa tươi thanh trùng Dalat Milk\n\nBình French Fress",
    "soLuong": "20gr\n\n200ml\n\n180ml",
    "buoc1": "Bước 1: Xay cà phê: Xay thô hạt cà phê. Không nên xay quá mịn vì khi ấn Piston sẽ khiến bột bị lẫn vào nước cà phê sau cùng.",
    "hinh1b1": "https://image.cooky.vn/recipe/g6/55849/s240x240/36c2508f-9475-44df-9dc9-1cbc29433f57.jpeg",
    "hinh2b1": "https://image.cooky.vn/recipe/g6/55849/s240x240/66da2ef9-4ece-4777-af5f-33dd91483f06.jpeg",
    "hinh3b1": null,
    "buoc2": "Bước 2: Pha cà phê: Ủ ấm bình French Fress với nước sôi trong 2 phút. Đổ cà phê đã xay vào, thêm 100ml nước sôi, khuấy nhẹ để cà phê ngấm và nở đều. Thêm tiếp 100ml nước sôi vào, lắp piston và ủ trong khoảng 4 phút. Sau thời gian trên, ấn từ từ piston xuống theo chiều thẳng đứng để nén phần bã cà phê xuống. Rót cà phê ra ly.",
    "hinh1b2": "https://image.cooky.vn/recipe/g6/55849/s240x240/92893a08-e795-4c55-a4ed-7f30a3027510.jpeg",
    "hinh2b2": "https://image.cooky.vn/recipe/g6/55849/s240x240/ad41a7db-c583-4851-9c80-214368510c78.jpeg",
    "hinh3b2": "https://image.cooky.vn/recipe/g6/55849/s240x240/9bc595c7-e161-4a6a-9ba5-11b5e2a1e770.jpeg",
    "buoc3": "Bước 3: Tạo bọt sữa: Hâm nóng 180ml sữa tươi thanh trùng Dalat Milk rồi đổ vào bình French Fress. Gắn piston vào và ấn kéo liên tục trong khoảng 15 - 20 giây để tạo bọt sữa. Sau đó, đổ sữa vào ly cà phê, thêm bọt sữa, bột cacao lên mặt ly và tạo hình tùy thích.",
    "hinh1b3": "https://image.cooky.vn/recipe/g6/55849/s240x240/f982c4c1-5090-4266-9f3c-887e5bc4a8aa.jpeg",
    "hinh2b3": "https://image.cooky.vn/recipe/g6/55849/s240x240/14d72a29-3fea-4f8a-8214-b711220a89c7.jpeg",
    "hinh3b3": "https://image.cooky.vn/recipe/g6/55849/s240x240/dc6a1410-caa4-4723-9571-e6e52d0f37c0.jpeg",
    "buoc4": "Bước 4: Cà phê thơm quyện cùng lớp bọt sữa béo mịn là một thức uống tuyệt vời để bắt đầu một ngày mới đầy năng lượng. Bạn có thể tăng thêm hương vị của tách cappuccino bằng cách thưởng thức nóng cùng đường hoặc bánh quy.",
    "hinh1b4": "https://image.cooky.vn/recipe/g6/55849/s240x240/99658ed1-eb56-4793-b12a-046a3cbac2cd.jpeg",
    "hinh2b4": "https://image.cooky.vn/recipe/g6/55849/s240x240/90a94c86-d01d-4ab7-a263-9b016bab172f.jpeg",
    "hinh3b4": "https://image.cooky.vn/recipe/g6/55849/s240x240/40977a9b-4ae5-4773-84eb-2390b22f33b4.jpeg",
    "buoc5": null,
    "hinh1b5": null,
    "hinh2b5": null,
    "hinh3b5": null
  }
]
